pythonRLSA/__init__.py
pythonRLSA/rlsa.py
pythonRLSA/rlsa_fast.cp37-win_amd64.pyd
pythonRLSA/test_rlsa_unittest.py
pythonRLSA/test_images/image.jpg
pythonRLSA/test_images/image.png
pythonRLSA/test_images/image1.jpg
pythonRLSA/test_images/image1.png
pythonRLSA/test_images/image1_rlsa_hori_vertial.jpg
pythonRLSA/test_images/image1_rlsa_horizontal.jpg
pythonRLSA/test_images/image1_rlsa_vertical.jpg
pythonRLSA/test_images/image2.jpg
pythonRLSA/test_images/image2_rlsa_hori_vertical.jpg
pythonRLSA/test_images/image2_rlsa_horizontal.jpg
pythonRLSA/test_images/image2_rlsa_vertical.jpg
pythonRLSA/test_images/image_rlsa_hori_verti.jpg
pythonRLSA/test_images/image_rlsa_horizontal.jpg
pythonRLSA/test_images/image_rlsa_vertical.jpg
pythonRLSA/test_images/unittest.png
pythonRLSA-1.0.0.dist-info/LICENSE
pythonRLSA-1.0.0.dist-info/METADATA
pythonRLSA-1.0.0.dist-info/WHEEL
pythonRLSA-1.0.0.dist-info/top_level.txt
pythonRLSA-1.0.0.dist-info/RECORD
