Metadata-Version: 2.1
Name: pythonRLSA
Version: 1.0.0
Summary: Python Run Length Smoothing Algorithm for Document Processing
Home-page: https://github.com/Vasistareddy/pythonRLSA
Author: VasistaReddy
Author-email: vasista.1245@gmail.com
License: UNKNOWN
Download-URL: https://github.com/Vasistareddy/pythonRLSA
Keywords: opencv,rlsa,image,documents,article,OCR,extraction
Platform: UNKNOWN
Classifier: Programming Language :: Python :: 3.5
Classifier: Topic :: Scientific/Engineering :: Image Recognition
Classifier: License :: OSI Approved :: MIT License
Classifier: Topic :: Software Development :: Version Control :: Git
Requires-Dist: numpy
